Metadata-Version: 1.1
Name: pytld
Version: 0.1.0
Summary: Tld is obtained by url or full domain name
Home-page: https://github.com/MyKings/pytld
Author: MyKings
Author-email: xsseroot@gmail.com
License: MPL 1.1/GPL 2.0/LGPL 2.1
Keywords: tld,top level domain names,python
Platform: UNKNOWN
Classifier: Programming Language :: Python
Classifier: Programming Language :: Python :: 2.6
Classifier: Programming Language :: Python :: 2.7
Classifier: Intended Audience :: Developers
Classifier: Operating System :: OS Independent
Classifier: License :: OSI Approved :: Mozilla Public License 1.1 (MPL 1.1)
Classifier: License :: OSI Approved :: GNU General Public License v2 (GPLv2)
Classifier: License :: OSI Approved :: GNU Lesser General Public License v2 or later (LGPLv2+)
